{
  "version": {
    "description1": "Config version number used for auto_regen_outdated.",
    "description2": "Do not modify.",
    "value": 1
  },
  "auto_regen_outdated": {
    "description": "Should this file automatically regenerate whenever the default options are changed?",
    "value": true
  },
  "enabled": {
    "description1": "Should Things spawn like vanilla mobs?",
    "description2": "Not recommended for the intended experience.",
    "value": false
  },
  "first_spawning_day": {
    "description1": "The first day that Things can start spawning naturally.",
    "description2": "This option treats the first day in a world as day 1, unlike the vanilla F3 screen.",
    "value": 4
  },
  "blood_crawler": {
    "enabled": true,
    "spawn_weight": 10,
    "minimum_group_size": 3,
    "maximum_group_size": 5
  },
  "crawler": {
    "enabled": true,
    "spawn_weight": 5,
    "minimum_group_size": 1,
    "maximum_group_size": 3
  },
  "juliette_thing": {
    "enabled": true,
    "spawn_weight": 5,
    "minimum_group_size": 1,
    "maximum_group_size": 2
  },
  "palmer_thing": {
    "enabled": true,
    "spawn_weight": 3,
    "minimum_group_size": 1,
    "maximum_group_size": 1
  },
  "split_face": {
    "enabled": true,
    "spawn_weight": 1,
    "minimum_group_size": 1,
    "maximum_group_size": 1
  },
  "blair_thing": {
    "enabled": true,
    "spawn_weight": 1,
    "minimum_group_size": 1,
    "maximum_group_size": 1
  },
  "dogbeast_spitter": {
    "enabled": true,
    "spawn_weight": 10,
    "minimum_group_size": 1,
    "maximum_group_size": 3
  },
  "dogbeast": {
    "enabled": true,
    "spawn_weight": 1,
    "minimum_group_size": 8,
    "maximum_group_size": 24
  },
  "impaler": {
    "enabled": true,
    "spawn_weight": 5,
    "minimum_group_size": 1,
    "maximum_group_size": 2
  },
  "prowler": {
    "enabled": true,
    "spawn_weight": 1,
    "minimum_group_size": 2,
    "maximum_group_size": 2
  },
  "beast": {
    "enabled": true,
    "spawn_weight": 1,
    "minimum_group_size": 1,
    "maximum_group_size": 1
  },
  "alien_thing": {
    "enabled": false,
    "spawn_weight": 1,
    "minimum_group_size": 1,
    "maximum_group_size": 1
  }
}